[{"line":2,"elements":[{"start_timestamp":"2024-05-15T12:55:13.894Z","line":13,"name":"User search for a job by passing with invalid job location","description":"","id":"job-search-with-invalid-job-location;user-search-for-a-job-by-passing-with-invalid-job-location;;2","after":[{"result":{"duration":265661200,"status":"passed"},"match":{"location":"hooks.Hooks.teardown()"}}],"type":"scenario","keyword":"Scenario Outline","steps":[{"result":{"duration":24158344500,"status":"passed"},"line":8,"name":"I am a job seeker on NHS Jobs website using \"chrome\" for invalid location search","match":{"arguments":[{"val":"\"chrome\"","offset":44}],"location":"StepDefinition.JobSearchInvalidLocation.nhs_home_page_invalid_location(java.lang.String)"},"keyword":"Given "},{"result":{"duration":1282097200,"status":"passed"},"line":9,"name":"I enter incorrect location in search","match":{"location":"StepDefinition.JobSearchInvalidLocation.user_enter_invalid_job_location()"},"keyword":"When "},{"result":{"duration":108040200,"status":"passed"},"line":10,"name":"I should get no location found","match":{"location":"StepDefinition.JobSearchInvalidLocation.user_view_search_results()"},"keyword":"Then "}],"tags":[{"name":"@jobsearchinvalidjoblocation"}]},{"start_timestamp":"2024-05-15T12:55:39.810Z","line":14,"name":"User search for a job by passing with invalid job location","description":"","id":"job-search-with-invalid-job-location;user-search-for-a-job-by-passing-with-invalid-job-location;;3","after":[{"result":{"duration":14103074200,"status":"passed"},"match":{"location":"hooks.Hooks.teardown()"}}],"type":"scenario","keyword":"Scenario Outline","steps":[{"result":{"duration":68978469300,"status":"passed"},"line":8,"name":"I am a job seeker on NHS Jobs website using \"firefox\" for invalid location search","match":{"arguments":[{"val":"\"firefox\"","offset":44}],"location":"StepDefinition.JobSearchInvalidLocation.nhs_home_page_invalid_location(java.lang.String)"},"keyword":"Given "},{"result":{"duration":16563867300,"status":"passed"},"line":9,"name":"I enter incorrect location in search","match":{"location":"StepDefinition.JobSearchInvalidLocation.user_enter_invalid_job_location()"},"keyword":"When "},{"result":{"duration":1404065300,"status":"passed"},"line":10,"name":"I should get no location found","match":{"location":"StepDefinition.JobSearchInvalidLocation.user_view_search_results()"},"keyword":"Then "}],"tags":[{"name":"@jobsearchinvalidjoblocation"}]},{"start_timestamp":"2024-05-15T12:57:20.918Z","line":15,"name":"User search for a job by passing with invalid job location","description":"","id":"job-search-with-invalid-job-location;user-search-for-a-job-by-passing-with-invalid-job-location;;4","after":[{"result":{"duration":780149500,"status":"passed"},"match":{"location":"hooks.Hooks.teardown()"}}],"type":"scenario","keyword":"Scenario Outline","steps":[{"result":{"duration":32216039600,"status":"passed"},"line":8,"name":"I am a job seeker on NHS Jobs website using \"edge\" for invalid location search","match":{"arguments":[{"val":"\"edge\"","offset":44}],"location":"StepDefinition.JobSearchInvalidLocation.nhs_home_page_invalid_location(java.lang.String)"},"keyword":"Given "},{"result":{"duration":1542779200,"status":"passed"},"line":9,"name":"I enter incorrect location in search","match":{"location":"StepDefinition.JobSearchInvalidLocation.user_enter_invalid_job_location()"},"keyword":"When "},{"result":{"duration":50548500,"status":"passed"},"line":10,"name":"I should get no location found","match":{"location":"StepDefinition.JobSearchInvalidLocation.user_view_search_results()"},"keyword":"Then "}],"tags":[{"name":"@jobsearchinvalidjoblocation"}]}],"name":"Job Search with invalid job location","description":"  As a job seeker\n  I want to search for jobs on a NHS portal with invalid job location\n  So that I can find no location found message","id":"job-search-with-invalid-job-location","keyword":"Feature","uri":"file:src/test/java/features/JobSearchInvalidLocation.feature","tags":[{"name":"@jobsearchinvalidjoblocation","type":"Tag","location":{"line":1,"column":1}}]},{"line":2,"elements":[{"start_timestamp":"2024-05-15T12:57:55.554Z","line":13,"name":"User search for a job by passing with invalid job title","description":"","id":"job-search-with-invalid-job-title;user-search-for-a-job-by-passing-with-invalid-job-title;;2","after":[{"result":{"duration":302505000,"status":"passed"},"match":{"location":"hooks.Hooks.teardown()"}}],"type":"scenario","keyword":"Scenario Outline","steps":[{"result":{"duration":13468729700,"status":"passed"},"line":8,"name":"I am a job seeker on NHS Jobs website using \"chrome\" for invalid title search","match":{"arguments":[{"val":"\"chrome\"","offset":44}],"location":"StepDefinition.JobSearchInvalidTitle.nhs_home_page(java.lang.String)"},"keyword":"Given "},{"result":{"duration":3092523400,"status":"passed"},"line":9,"name":"I enter incorrect job title in search","match":{"location":"StepDefinition.JobSearchInvalidTitle.user_enter_incorrect_job_title()"},"keyword":"When "},{"result":{"duration":45419100,"status":"passed"},"line":10,"name":"I should get no results found","match":{"location":"StepDefinition.JobSearchInvalidTitle.user_view_search_results()"},"keyword":"Then "}],"tags":[{"name":"@jobsearchinvalidjobtitle"}]},{"start_timestamp":"2024-05-15T12:58:12.480Z","line":14,"name":"User search for a job by passing with invalid job title","description":"","id":"job-search-with-invalid-job-title;user-search-for-a-job-by-passing-with-invalid-job-title;;3","after":[{"result":{"duration":8787660900,"status":"passed"},"match":{"location":"hooks.Hooks.teardown()"}}],"type":"scenario","keyword":"Scenario Outline","steps":[{"result":{"duration":27353018300,"status":"passed"},"line":8,"name":"I am a job seeker on NHS Jobs website using \"firefox\" for invalid title search","match":{"arguments":[{"val":"\"firefox\"","offset":44}],"location":"StepDefinition.JobSearchInvalidTitle.nhs_home_page(java.lang.String)"},"keyword":"Given "},{"result":{"duration":6077905500,"status":"passed"},"line":9,"name":"I enter incorrect job title in search","match":{"location":"StepDefinition.JobSearchInvalidTitle.user_enter_incorrect_job_title()"},"keyword":"When "},{"result":{"duration":269666600,"status":"passed"},"line":10,"name":"I should get no results found","match":{"location":"StepDefinition.JobSearchInvalidTitle.user_view_search_results()"},"keyword":"Then "}],"tags":[{"name":"@jobsearchinvalidjobtitle"}]},{"start_timestamp":"2024-05-15T12:58:54.999Z","line":15,"name":"User search for a job by passing with invalid job title","description":"","id":"job-search-with-invalid-job-title;user-search-for-a-job-by-passing-with-invalid-job-title;;4","after":[{"result":{"duration":474438400,"status":"passed"},"match":{"location":"hooks.Hooks.teardown()"}}],"type":"scenario","keyword":"Scenario Outline","steps":[{"result":{"duration":23061469000,"status":"passed"},"line":8,"name":"I am a job seeker on NHS Jobs website using \"edge\" for invalid title search","match":{"arguments":[{"val":"\"edge\"","offset":44}],"location":"StepDefinition.JobSearchInvalidTitle.nhs_home_page(java.lang.String)"},"keyword":"Given "},{"result":{"duration":1651836300,"status":"passed"},"line":9,"name":"I enter incorrect job title in search","match":{"location":"StepDefinition.JobSearchInvalidTitle.user_enter_incorrect_job_title()"},"keyword":"When "},{"result":{"duration":98375000,"status":"passed"},"line":10,"name":"I should get no results found","match":{"location":"StepDefinition.JobSearchInvalidTitle.user_view_search_results()"},"keyword":"Then "}],"tags":[{"name":"@jobsearchinvalidjobtitle"}]}],"name":"Job Search with invalid job title","description":"  As a job seeker\n  I want to search for jobs on a NHS portal with invalid job title\n  So that I can find no result found message","id":"job-search-with-invalid-job-title","keyword":"Feature","uri":"file:src/test/java/features/JobSearchInvalidTitle.feature","tags":[{"name":"@jobsearchinvalidjobtitle","type":"Tag","location":{"line":1,"column":1}}]},{"line":2,"elements":[{"start_timestamp":"2024-05-15T12:59:20.319Z","line":14,"name":"User search for a job by passing both title,location and distance in job filter","description":"","id":"job-search;user-search-for-a-job-by-passing-both-title-location-and-distance-in-job-filter;;2","after":[{"result":{"duration":403068300,"status":"passed"},"match":{"location":"hooks.Hooks.teardown()"}}],"type":"scenario","keyword":"Scenario Outline","steps":[{"result":{"duration":14423781100,"status":"passed"},"line":8,"name":"I am a job seeker on NHS Jobs website using \"chrome\" for job search","match":{"arguments":[{"val":"\"chrome\"","offset":44}],"location":"StepDefinition.JobSearchValidData.nhs_home_page(java.lang.String)"},"keyword":"Given "},{"result":{"duration":1173720100,"status":"passed"},"line":9,"name":"I put search preference into the Search functionality","match":{"location":"StepDefinition.JobSearchValidData.user_enter_search_preference()"},"keyword":"When "},{"result":{"duration":294711900,"status":"passed"},"line":10,"name":"I should get a list of jobs which matches my preferences","match":{"location":"StepDefinition.JobSearchValidData.user_view_search_results()"},"keyword":"Then "},{"result":{"duration":752636000,"status":"passed"},"line":11,"name":"sort my search results with the newest Date Posted","match":{"location":"StepDefinition.JobSearchValidData.user_filter_by_recent_date()"},"keyword":"And "}],"tags":[{"name":"@jobsearch"}]},{"start_timestamp":"2024-05-15T12:59:37.370Z","line":15,"name":"User search for a job by passing both title,location and distance in job filter","description":"","id":"job-search;user-search-for-a-job-by-passing-both-title-location-and-distance-in-job-filter;;3","after":[{"result":{"duration":3352452600,"status":"passed"},"match":{"location":"hooks.Hooks.teardown()"}}],"type":"scenario","keyword":"Scenario Outline","steps":[{"result":{"duration":17481466900,"status":"passed"},"line":8,"name":"I am a job seeker on NHS Jobs website using \"firefox\" for job search","match":{"arguments":[{"val":"\"firefox\"","offset":44}],"location":"StepDefinition.JobSearchValidData.nhs_home_page(java.lang.String)"},"keyword":"Given "},{"result":{"duration":1584559000,"status":"passed"},"line":9,"name":"I put search preference into the Search functionality","match":{"location":"StepDefinition.JobSearchValidData.user_enter_search_preference()"},"keyword":"When "},{"result":{"duration":100626200,"status":"passed"},"line":10,"name":"I should get a list of jobs which matches my preferences","match":{"location":"StepDefinition.JobSearchValidData.user_view_search_results()"},"keyword":"Then "},{"result":{"duration":805532600,"status":"passed"},"line":11,"name":"sort my search results with the newest Date Posted","match":{"location":"StepDefinition.JobSearchValidData.user_filter_by_recent_date()"},"keyword":"And "}],"tags":[{"name":"@jobsearch"}]},{"start_timestamp":"2024-05-15T13:00:00.725Z","line":16,"name":"User search for a job by passing both title,location and distance in job filter","description":"","id":"job-search;user-search-for-a-job-by-passing-both-title-location-and-distance-in-job-filter;;4","after":[{"result":{"duration":327714300,"status":"passed"},"match":{"location":"hooks.Hooks.teardown()"}}],"type":"scenario","keyword":"Scenario Outline","steps":[{"result":{"duration":11752221200,"status":"passed"},"line":8,"name":"I am a job seeker on NHS Jobs website using \"edge\" for job search","match":{"arguments":[{"val":"\"edge\"","offset":44}],"location":"StepDefinition.JobSearchValidData.nhs_home_page(java.lang.String)"},"keyword":"Given "},{"result":{"duration":1097329800,"status":"passed"},"line":9,"name":"I put search preference into the Search functionality","match":{"location":"StepDefinition.JobSearchValidData.user_enter_search_preference()"},"keyword":"When "},{"result":{"duration":114034400,"status":"passed"},"line":10,"name":"I should get a list of jobs which matches my preferences","match":{"location":"StepDefinition.JobSearchValidData.user_view_search_results()"},"keyword":"Then "},{"result":{"duration":2002199100,"status":"passed"},"line":11,"name":"sort my search results with the newest Date Posted","match":{"location":"StepDefinition.JobSearchValidData.user_filter_by_recent_date()"},"keyword":"And "}],"tags":[{"name":"@jobsearch"}]}],"name":"Job Search","description":"  As a job seeker\n  I want to search for jobs on a NHS portal\n  So that I can find relevant job opportunities","id":"job-search","keyword":"Feature","uri":"file:src/test/java/features/JobSearchScenarios.feature","tags":[{"name":"@jobsearch","type":"Tag","location":{"line":1,"column":1}}]}]